MANIFEST.in
README.md
requirements.txt
setup.cfg
setup.py
mesoscope/__init__.py
mesoscope/cli.py
mesoscope/data.py
mesoscope/main.py
mesoscope/metadata.py
mesoscope.egg-info/PKG-INFO
mesoscope.egg-info/SOURCES.txt
mesoscope.egg-info/dependency_links.txt
mesoscope.egg-info/entry_points.txt
mesoscope.egg-info/requires.txt
mesoscope.egg-info/top_level.txt
mesoscope/commands/__init__.py
mesoscope/commands/convert.py
test/test_module.py